MANIFEST.in
README.md
requirements.txt
setup.cfg
setup.py
familyapp/__init__.py
familyapp/bot.py
familyapp.py.egg-info/PKG-INFO
familyapp.py.egg-info/SOURCES.txt
familyapp.py.egg-info/dependency_links.txt
familyapp.py.egg-info/requires.txt
familyapp.py.egg-info/top_level.txt