Metadata-Version: 1.0
Name: familyapp.py
Version: 0.0.13
Summary: A python wrapper for the FamilyApp API
Home-page: https://github.com/piotrgiedziun/familyapp.py
Author: Piotr Giedziun
Author-email: piotrgiedziun@gmail.com
License: MIT
Platform: UNKNOWN
